mcp_jamie_test3/__init__.py
mcp_jamie_test3/server.py
mcp_jamie_test3-2.0.1.dist-info/METADATA
mcp_jamie_test3-2.0.1.dist-info/WHEEL
mcp_jamie_test3-2.0.1.dist-info/entry_points.txt
mcp_jamie_test3-2.0.1.dist-info/RECORD
