Metadata-Version: 2.4
Name: mcp-jamie-test3
Version: 2.0.1
Summary: jamie test
Requires-Python: >=3.10
Requires-Dist: httpx>=0.28.1
Requires-Dist: mcp[cli]>=1.9.2
